{"data": {"product_name": "Tecno I3 Pro ", "product_model": "I3 Pro ", "product_brand": "Tecno", "product_id": "ZToxMjkzMg", "product_ratings": "4", "product_mrp": "10590", "product_category": "mobile", "product_sub_category": "mobile", "is_available": true, "available_colors": ["All Colours", "Gold"], "product_images": ["https://images-api.datayuge.in/image/dHI6dy0xNDAwLGgtMTQwMCxjLWF0X21heC8xMjkzMi05MC0x.jpg", "https://images-api.datayuge.in/image/dHI6dy0xNDAwLGgtMTQwMCxjLWF0X21heC8xMjkzMi05MC0y.jpg", "https://images-api.datayuge.in/image/dHI6dy0xNDAwLGgtMTQwMCxjLWF0X21heC8xMjkzMi05MC0z.jpg", "https://images-api.datayuge.in/image/dHI6dy0xNDAwLGgtMTQwMCxjLWF0X21heC8xMjkzMi05MC00.jpg"], "is_comparable": true, "spec_available": true, "review_available": true, "stores": [{"amazon": {"product_store": "Amazon.in", "product_store_logo": "https://images-api.datayuge.in/image/YW1hem9uX3N0b3JlLnBuZw.png", "product_store_url": "https://price-api.datayuge.com/redirect?id=aHR0cHM6Ly93d3cuYW1hem9uLmluL2dwL29mZmVyLWxpc3RpbmcvQjA3NkcySlZWUi8_JnRhZz1wcmljZXl1Z2UwZC0yMQ", "product_price": "7337", "product_mrp": "0", "product_offer": "", "product_color": "", "product_delivery": "2-3", "product_delivery_cost": "0", "is_emi": "0", "is_cod": "0", "return_time": "10 Days"}}, {"flipkart": {"product_store": "Flipkart", "product_store_logo": "https://images-api.datayuge.in/image/ZmxpcGthcnRfc3RvcmUucG5n.png", "product_store_url": "https://price-api.datayuge.com/redirect?id=aHR0cHM6Ly9kbC5mbGlwa2FydC5jb20vZGwvdGVjbm8taTMtcHJvLWdvbGQtMTYtZ2IvcC9pdG1leXpuY3ZqenJnZ2ZmP3BpZD1NT0JFWVdDUFFVQkhSWUo0JmFmZmlkPWFydW5iYWJ1bA", "product_price": "10000", "product_mrp": "10000", "product_offer": "10% off on AU Bank Debit Cards.5% Cashback on Flipkart Axis Bank Card.No Cost EMI on Flipkart Axis Bank Credit Card.", "product_color": "gold", "product_delivery": "3-4", "product_delivery_cost": "0", "is_emi": "0", "is_cod": "1", "return_time": "10 Days"}}, {"snapdeal": []}, {"ebay": []}, {"paytm": []}, {"croma": []}, {"yebhi": []}, {"indiatimes": []}, {"homeshop18": []}, {"naaptol": []}, {"infibeam": []}, {"tatacliq": []}, {"shopclues": []}, {"paytmmall": []}, {"gadgets360": []}, {"mi": []}, {"2gud": []}], "specs": ["5  inch Screen", "3 GB RAM", "16 GB ROM", "Android 7.0 Nougat OS", "Dual SIM"]}}