{"data": {"product_name": "SanDisk Ultra Fit 32GB USB 3.0 Pen Drive", "product_model": "Ultra Fit 32GB USB 3.0 Pen Drive", "product_brand": "SanDisk", "product_id": "ZTo1NjYzNzM", "product_ratings": "4.3", "product_mrp": "5120", "product_category": "computer", "product_sub_category": "computer-pendrive", "is_available": true, "available_colors": ["All Colours"], "product_images": ["https://images-api.datayuge.in/image/dHI6dy0xNDAwLGgtMTQwMCxjLWF0X21heC81NjYzNzMtMTgwLTE.jpg", "https://images-api.datayuge.in/image/dHI6dy0xNDAwLGgtMTQwMCxjLWF0X21heC81NjYzNzMtMTgwLTI.jpg", "https://images-api.datayuge.in/image/dHI6dy0xNDAwLGgtMTQwMCxjLWF0X21heC81NjYzNzMtMTgwLTM.jpg"], "is_comparable": true, "spec_available": true, "review_available": true, "stores": [{"amazon": {"product_store": "Amazon.in", "product_store_logo": "https://images-api.datayuge.in/image/YW1hem9uX3N0b3JlLnBuZw.png", "product_store_url": "https://price-api.datayuge.com/redirect?id=aHR0cHM6Ly93d3cuYW1hem9uLmluL2dwL29mZmVyLWxpc3RpbmcvQjAxQkdURzQxVy8_JnRhZz1wcmljZXl1Z2UwZC0yMQ", "product_price": "1699", "product_mrp": "1999", "product_offer": "", "product_color": "", "product_delivery": "2-3", "product_delivery_cost": "0", "is_emi": "0", "is_cod": "0", "return_time": "10 Days"}}, {"flipkart": []}, {"snapdeal": []}, {"ebay": []}, {"paytm": []}, {"croma": []}, {"yebhi": []}, {"indiatimes": []}, {"homeshop18": []}, {"naaptol": []}, {"infibeam": []}, {"tatacliq": []}, {"shopclues": []}, {"paytmmall": []}, {"gadgets360": []}, {"mi": []}, {"2gud": []}], "specs": ["32 GB  Capacity", "USB 2.0/3.0"]}}