{"data": {"product_name": "SanDisk Cruzer Blade 128GB USB 2.0 Pen Drive", "product_model": "Cruzer Blade 128GB USB 2.0 Pen Drive", "product_brand": "SanDisk", "product_id": "ZTo1NjYzNjc", "product_ratings": "4.2", "product_mrp": "3890", "product_category": "computer", "product_sub_category": "computer-pendrive", "is_available": true, "available_colors": ["All Colours", "Black"], "product_images": ["https://images-api.datayuge.in/image/dHI6dy0xNDAwLGgtMTQwMCxjLWF0X21heC81NjYzNjctMzMtMQ.jpg", "https://images-api.datayuge.in/image/dHI6dy0xNDAwLGgtMTQwMCxjLWF0X21heC81NjYzNjctMzMtMg.jpg", "https://images-api.datayuge.in/image/dHI6dy0xNDAwLGgtMTQwMCxjLWF0X21heC81NjYzNjctMzMtMw.jpg"], "is_comparable": true, "spec_available": true, "review_available": true, "stores": [{"amazon": {"product_store": "Amazon.in", "product_store_logo": "https://images-api.datayuge.in/image/YW1hem9uX3N0b3JlLnBuZw.png", "product_store_url": "https://price-api.datayuge.com/redirect?id=aHR0cHM6Ly93d3cuYW1hem9uLmluL2dwL29mZmVyLWxpc3RpbmcvQjAwUk0xRUMxUy8_JnRhZz1wcmljZXl1Z2UwZC0yMQ", "product_price": "1350", "product_mrp": "3890", "product_offer": "", "product_color": "", "product_delivery": "2-3", "product_delivery_cost": "0", "is_emi": "0", "is_cod": "0", "return_time": "10 Days"}}, {"flipkart": {"product_store": "Flipkart", "product_store_logo": "https://images-api.datayuge.in/image/ZmxpcGthcnRfc3RvcmUucG5n.png", "product_store_url": "https://price-api.datayuge.com/redirect?id=aHR0cHM6Ly9kbC5mbGlwa2FydC5jb20vZGwvc2FuZGlzay1jcnV6ci1ibGFkZS0xMjgtZ2ItcGVuLWRyaXZlL3AvaXRtMmViM2I1ODIyNWViYz9waWQ9QUNDRk45MjNIRjdWNkdZWSZhZmZpZD1hcnVuYmFidWw", "product_price": "1195", "product_mrp": "3100", "product_offer": "5% Cashback on Flipkart Axis Bank Card.", "product_color": "", "product_delivery": "3-4", "product_delivery_cost": "0", "is_emi": "0", "is_cod": "1", "return_time": "10 Days"}}, {"snapdeal": []}, {"ebay": []}, {"paytm": []}, {"croma": []}, {"yebhi": []}, {"indiatimes": []}, {"homeshop18": []}, {"naaptol": []}, {"infibeam": []}, {"tatacliq": {"product_store": "Tata CliQ", "product_store_logo": "https://images-api.datayuge.in/image/dGF0YWNsaXFfc3RvcmUucG5n.png", "product_store_url": "https://www.tatacliq.com/sandisk-cruzer-blade-cz50-128-gb-usb-flash-drive-black/p-mp000000000273597", "product_price": "1129", "product_mrp": "0", "product_offer": "", "product_color": "", "product_delivery": "4-5", "product_delivery_cost": "0", "is_emi": "0", "is_cod": "0", "return_time": ""}}, {"shopclues": []}, {"paytmmall": []}, {"gadgets360": []}, {"mi": []}, {"2gud": []}], "specs": ["128 GB  Capacity", "USB 2.0"]}}