{"data": {"product_name": "Godrej RF GF 2604 PTRI 260 L 4 Star Inverter Frost Free Double Door Refrigerator", "product_model": "RF GF 2604 PTRI 260 L 4 Star Inverter Frost Free Double Door Refrigerator", "product_brand": "Godrej", "product_id": "ZTo1NTgxNzY", "product_ratings": "4.2", "product_mrp": "34200", "product_category": "appliance", "product_sub_category": "refrigerators", "is_available": true, "available_colors": ["All Colours"], "product_images": ["https://images-api.datayuge.in/image/dHI6dy0xNDAwLGgtMTQwMCxjLWF0X21heC81NTgxNzYtMTAtMQ.jpg"], "is_comparable": true, "spec_available": true, "review_available": true, "stores": [{"amazon": {"product_store": "Amazon.in", "product_store_logo": "https://images-api.datayuge.in/image/YW1hem9uX3N0b3JlLnBuZw.png", "product_store_url": "https://price-api.datayuge.com/redirect?id=aHR0cHM6Ly93d3cuYW1hem9uLmluL2dwL29mZmVyLWxpc3RpbmcvQjA3Vk5MM0pYMy8_JnRhZz1wcmljZXl1Z2UwZC0yMQ", "product_price": "22490", "product_mrp": "34200", "product_offer": "", "product_color": "", "product_delivery": "2-3", "product_delivery_cost": "0", "is_emi": "0", "is_cod": "0", "return_time": "10 Days"}}, {"flipkart": []}, {"snapdeal": []}, {"ebay": []}, {"paytm": []}, {"croma": []}, {"yebhi": []}, {"indiatimes": []}, {"homeshop18": []}, {"naaptol": []}, {"infibeam": []}, {"tatacliq": {"product_store": "Tata CliQ", "product_store_logo": "https://images-api.datayuge.in/image/dGF0YWNsaXFfc3RvcmUucG5n.png", "product_store_url": "https://www.tatacliq.com/godrej-260l-inverter-4-star-2019-frost-free-double-door-refrigerator-steel-yarn,-rf-gf-2604-ptri/p-mp000000006553456", "product_price": "20990", "product_mrp": "0", "product_offer": "Exciting EMI offers ", "product_color": "", "product_delivery": "4-5", "product_delivery_cost": "0", "is_emi": "0", "is_cod": "0", "return_time": ""}}, {"shopclues": []}, {"paytmmall": []}, {"gadgets360": []}, {"mi": []}, {"2gud": []}], "specs": ["Double Door  Refrigerator", "260  Liter Capacity", "Frost Free", "4 Star  Rating"]}}